{
  "recipes": [
    {
      "id": "e3340fb5-51ae-4bc4-bfb6-5c39a006c65b",
      "name": "dsads",
      "image": "https://www.behance.net/gallery/102172483/DELISH/modules/588367807",
      "preparationTime": "20 minutos",
      "yield": "5 pessoas",
      "level": "Intermediário",
      "category": "deserts",
      "ingredients": [
        "wewqed",
        "dqwwq",
        "fq",
        "32",
        "r",
        "",
        "r"
      ],
      "directions": [
        "dwqwfq",
        "f332f",
        "w",
        "3f3",
        "f32",
        "23ff",
        "wef"
      ],
      "isFavorite": false,
      "createdAt": "2021-04-30T01:36:11.364Z",
      "updatedAt": "2021-04-30T01:47:11.113Z"
    },
    {
      "id": "2deac066-0efe-4fb5-b3b1-3703ad767e00",
      "name": "adasadas",
      "image": "https://www.behance.net/gallery/102172483/DELISH/modules/588367807",
      "preparationTime": "dasdasasa",
      "yield": "dasdsaa",
      "level": "Intermediário",
      "category": "meal",
      "ingredients": "dsadasdsaddsa\ndasd\nassa\nd\naa\nddaasd",
      "directions": "dadsas\nsa\nds\ns\na",
      "isFavorite": false,
      "createdAt": "2021-04-30T01:56:30.085Z",
      "updatedAt": "2021-04-30T01:56:30.085Z"
    }
  ]
}